LICENSE
README.md
pyproject.toml
setup.py
src/pymusic/__init__.py
src/pymusic/py.typed
src/pymusic/big_array/__init__.py
src/pymusic/big_array/array.py
src/pymusic/big_array/caching.py
src/pymusic/big_array/derived.py
src/pymusic/big_array/diff.py
src/pymusic/big_array/exceptions.py
src/pymusic/big_array/file.py
src/pymusic/big_array/helpers.py
src/pymusic/big_array/index.py
src/pymusic/big_array/music.py
src/pymusic/big_array/physics.py
src/pymusic/big_array/spec.py
src/pymusic/eos/__init__.py
src/pymusic/eos/interp.py
src/pymusic/eos/mesa.py
src/pymusic/eos/mesa_formats.py
src/pymusic/eos/music_formats.py
src/pymusic/eos/table.py
src/pymusic/eos/variables.py
src/pymusic/grid/__init__.py
src/pymusic/grid/grid1d.py
src/pymusic/grid/grids.py
src/pymusic/io/__init__.py
src/pymusic/io/music.py
src/pymusic/math/__init__.py
src/pymusic/math/complex.py
src/pymusic/math/find_zeros.py
src/pymusic/math/slicing.py
src/pymusic/math/spherical_quadrature.py
src/pymusic/opacity/__init__.py
src/pymusic/opacity/mesa.py
src/pymusic/opacity/music_formats.py
src/pymusic/opacity/table.py
src/pymusic/opacity/variables.py
src/pymusic/particles/__init__.py
src/pymusic/particles/dumps.py
src/pymusic/particles/events.py
src/pymusic/particles/plotting.py
src/pymusic/particles/rm2017.py
src/pymusic/particles/trajectory.py
src/pymusic/particles/transmat.py
src/pymusic/plotting/__init__.py
src/pymusic/plotting/array.py
src/pymusic/plotting/figure.py
src/pymusic/plotting/lic.c
src/pymusic/plotting/lic.pyx
src/pymusic/plotting/movies.py
src/pymusic/plotting/particles.py
src/pymusic/plotting/stretch_funcs.py
src/pymusic/spec/__init__.py
src/pymusic/spec/fft.py
src/pymusic/spec/nufft.py
src/pymusic/spec/spherical_harmonics.py
src/pymusic/spec/wedge_harmonics.py
src/pymusic/spec/wedge_harmonics_array.py
src/pymusic/spec/windows.py
src/pymusic/studies/__init__.py
src/pymusic/studies/nufft/__init__.py
src/pymusic/studies/nufft/study-cheb-nufft.py
src/pymusic/studies/nufft/study-lowrank-exp.py
src/pymusic_astro.egg-info/PKG-INFO
src/pymusic_astro.egg-info/SOURCES.txt
src/pymusic_astro.egg-info/dependency_links.txt
src/pymusic_astro.egg-info/requires.txt
src/pymusic_astro.egg-info/top_level.txt