Metadata-Version: 2.1
Name: pymusic-astro
Version: 3.0.0
Summary: MUSIC output files processing
Author: Adrien Morison
Author-email: Thomas Guillet <t.a.guillet@exeter.ac.uk>
License: BSD 3-Clause License
Project-URL: homepage, https://bitbucket.org/glt/pymusic/
Classifier: Development Status :: 3 - Alpha
Classifier: Intended Audience :: Science/Research
Classifier: License :: OSI Approved
Classifier: Programming Language :: Python :: 3 :: Only
Classifier: Programming Language :: Python :: 3.10
Classifier: Programming Language :: Python :: 3.11
Classifier: Programming Language :: Python :: 3.12
Classifier: Programming Language :: Python :: 3.13
Requires-Python: >=3.10
License-File: LICENSE
Requires-Dist: lazympl~=0.1.2
Requires-Dist: numpy~=2.1
Requires-Dist: scipy~=1.14
Requires-Dist: pandas~=2.2
Requires-Dist: h5py~=3.12
Requires-Dist: matplotlib~=3.9
Requires-Dist: tqdm>=4.66
Requires-Dist: xarray>=2024.10
Requires-Dist: music_pykg~=7.1.0
